pz_rail_lephare-1.1.8.dist-info/licenses/LICENSE
rail/estimation/algos/lephare.py
rail/lephare/README.md
rail/lephare/__init__.py
rail/lephare/_version.py
pz_rail_lephare-1.1.8.dist-info/METADATA
pz_rail_lephare-1.1.8.dist-info/WHEEL
pz_rail_lephare-1.1.8.dist-info/top_level.txt
pz_rail_lephare-1.1.8.dist-info/RECORD
